hackingBuddyGPT/__init__.py
hackingBuddyGPT/capabilities/__init__.py
hackingBuddyGPT/capabilities/capability.py
hackingBuddyGPT/capabilities/http_request.py
hackingBuddyGPT/capabilities/psexec_run_command.py
hackingBuddyGPT/capabilities/psexec_test_credential.py
hackingBuddyGPT/capabilities/record_note.py
hackingBuddyGPT/capabilities/ssh_run_command.py
hackingBuddyGPT/capabilities/ssh_test_credential.py
hackingBuddyGPT/capabilities/submit_flag.py
hackingBuddyGPT/capabilities/submit_http_method.py
hackingBuddyGPT/capabilities/yamlFile.py
hackingBuddyGPT/cli/__init__.py
hackingBuddyGPT/cli/stats.py
hackingBuddyGPT/cli/viewer.py
hackingBuddyGPT/cli/wintermute.py
hackingBuddyGPT/usecases/__init__.py
hackingBuddyGPT/usecases/agents.py
hackingBuddyGPT/usecases/base.py
hackingBuddyGPT/usecases/examples/__init__.py
hackingBuddyGPT/usecases/examples/agent.py
hackingBuddyGPT/usecases/examples/agent_with_state.py
hackingBuddyGPT/usecases/examples/get_hint_from_lse.txt
hackingBuddyGPT/usecases/examples/hintfile.py
hackingBuddyGPT/usecases/examples/lse.py
hackingBuddyGPT/usecases/examples/next_cmd.txt
hackingBuddyGPT/usecases/privesc/__init__.py
hackingBuddyGPT/usecases/privesc/common.py
hackingBuddyGPT/usecases/privesc/linux.py
hackingBuddyGPT/usecases/privesc/windows.py
hackingBuddyGPT/usecases/privesc/templates/analyze_cmd.txt
hackingBuddyGPT/usecases/privesc/templates/query_next_command.txt
hackingBuddyGPT/usecases/privesc/templates/update_state.txt
hackingBuddyGPT/usecases/web/__init__.py
hackingBuddyGPT/usecases/web/simple.py
hackingBuddyGPT/usecases/web/with_explanation.py
hackingBuddyGPT/usecases/web_api_testing/__init__.py
hackingBuddyGPT/usecases/web_api_testing/simple_openapi_documentation.py
hackingBuddyGPT/usecases/web_api_testing/simple_web_api_testing.py
hackingBuddyGPT/usecases/web_api_testing/documentation/__init__.py
hackingBuddyGPT/usecases/web_api_testing/documentation/openapi_specification_handler.py
hackingBuddyGPT-0.3.1.dist-info/LICENSE
hackingBuddyGPT-0.3.1.dist-info/METADATA
hackingBuddyGPT-0.3.1.dist-info/WHEEL
hackingBuddyGPT-0.3.1.dist-info/entry_points.txt
hackingBuddyGPT-0.3.1.dist-info/top_level.txt
hackingBuddyGPT-0.3.1.dist-info/RECORD
