Metadata-Version: 2.1
Name: hackingBuddyGPT
Version: 0.3.1
Summary: Helping Ethical Hackers use LLMs in 50 lines of code
Author-email: Andreas Happe <andreas@offensive.one>
Maintainer-email: Andreas Happe <andreas@offensive.one>, Juergen Cito <juergen.cito@tuwiena.c.at>
License: MIT License
Project-URL: Homepage, https://www.hackingbuddy.ai
Project-URL: Documentation, https://docs.hackingbuddy.ai
Project-URL: Repository, https://github.com/ipa-lab/hackingBuddyGPT
Project-URL: Bug Tracker, https://github.com/ipa-lab/hackingBuddyGPT/issues
Keywords: hacking,pen-testing,LLM,AI,agent
Classifier: Programming Language :: Python :: 3
Classifier: License :: OSI Approved :: MIT License
Classifier: Operating System :: OS Independent
Classifier: Development Status :: 4 - Beta
Requires-Python: >=3.10
License-File: LICENSE
Requires-Dist: fabric ==3.2.2
Requires-Dist: Mako ==1.3.2
Requires-Dist: requests ==2.32.0
Requires-Dist: rich ==13.7.1
Requires-Dist: tiktoken ==0.6.0
Requires-Dist: instructor ==1.3.5
Requires-Dist: PyYAML ==6.0.1
Requires-Dist: python-dotenv ==1.0.1
Requires-Dist: pypsexec ==0.3.0
Requires-Dist: pydantic ==2.8.2
Requires-Dist: openai ==1.28.0
Requires-Dist: BeautifulSoup4
Requires-Dist: nltk
Provides-Extra: testing
Requires-Dist: pytest ; extra == 'testing'
Requires-Dist: pytest-mock ; extra == 'testing'
